mbientlab/__init__.py
mbientlab/metawear/__init__.py
mbientlab/metawear/cbindings.py
mbientlab/metawear/libmetawear.so
mbientlab/metawear/libmetawear.so.0
mbientlab/metawear/libmetawear.so.0.10.0
metawear-0.1.1.dist-info/DESCRIPTION.rst
metawear-0.1.1.dist-info/METADATA
metawear-0.1.1.dist-info/RECORD
metawear-0.1.1.dist-info/WHEEL
metawear-0.1.1.dist-info/dependency_links.txt
metawear-0.1.1.dist-info/metadata.json
metawear-0.1.1.dist-info/top_level.txt
