Metadata-Version: 2.0
Name: metawear
Version: 0.1.1
Summary: Python bindings for the MetaWear C++ SDK
Home-page: https://github.com/mbientlab/MetaWear-SDK-Python
Author: MbientLab
Author-email: hello@mbientlab.com
License: UNKNOWN
Keywords: sensors,mbientlab,metawear,bluetooth le,native
Platform: UNKNOWN
Classifier: Development Status :: 4 - Beta
Classifier: Intended Audience :: Developers
Classifier: Operating System :: POSIX :: Linux
Classifier: Programming Language :: Python :: 2.7
Classifier: Programming Language :: Python :: 3
Requires-Python: >=2.7
Requires-Dist: gattlib (==0.20160216)
Requires-Dist: requests
